init_fastapi/__init__.py
init_fastapi/__main__.py
init_fastapi/config.py
init_fastapi/constants.py
init_fastapi/context.py
init_fastapi/generator.py
init_fastapi/helpers.py
init_fastapi/main.py
init_fastapi/templates/__init__.py
init_fastapi/templates/project/__init__.py
init_fastapi/templates/project/cookiecutter.json
init_fastapi/templates/project/hooks/post_gen_project.py
init_fastapi/templates/project/{{ cookiecutter.folder_name }}/.pre-commit-config.yaml
init_fastapi/templates/project/{{ cookiecutter.folder_name }}/LICENSE
init_fastapi/templates/project/{{ cookiecutter.folder_name }}/README.md
init_fastapi/templates/project/{{ cookiecutter.folder_name }}/docker-compose.yaml
init_fastapi/templates/project/{{ cookiecutter.folder_name }}/pyproject.toml
init_fastapi/templates/project/{{ cookiecutter.folder_name }}/setup.cfg
init_fastapi/templates/project/{{ cookiecutter.folder_name }}/{{ cookiecutter.gitignore }}
init_fastapi/templates/project/{{ cookiecutter.folder_name }}/.vscode/launch.json
init_fastapi/templates/project/{{ cookiecutter.folder_name }}/.vscode/settings.json
init_fastapi/templates/project/{{ cookiecutter.folder_name }}/src/Dockerfile
init_fastapi/templates/project/{{ cookiecutter.folder_name }}/src/requirements.txt
init_fastapi/templates/project/{{ cookiecutter.folder_name }}/src/{{ cookiecutter.env }}
init_fastapi/templates/project/{{ cookiecutter.folder_name }}/src/app/main.py
init_fastapi/templates/project/{{ cookiecutter.folder_name }}/src/app/core/__init__.py
init_fastapi/templates/project/{{ cookiecutter.folder_name }}/src/app/core/config.py
init_fastapi/templates/project/{{ cookiecutter.folder_name }}/src/app/models/attributes/health.py
init_fastapi/templates/project/{{ cookiecutter.folder_name }}/src/app/models/domains/health.py
init_fastapi/templates/project/{{ cookiecutter.folder_name }}/src/app/models/schemas/health.py
init_fastapi/templates/project/{{ cookiecutter.folder_name }}/src/app/routers/health.py
init_fastapi-1.0.2.5.dist-info/METADATA
init_fastapi-1.0.2.5.dist-info/WHEEL
init_fastapi-1.0.2.5.dist-info/entry_points.txt
init_fastapi-1.0.2.5.dist-info/licenses/LICENSE
init_fastapi-1.0.2.5.dist-info/RECORD
