Metadata-Version: 2.1
Name: init-fastapi
Version: 1.0.2.5
Summary: Managing FastAPI projects made easy.
Project-URL: Homepage, https://github.com/toantranct94/init-fastapi
Project-URL: Documentation, https://github.com/toantranct94/init-fastapi
Project-URL: Source, https://github.com/toantranct94/init-fastapi
Author-email: Tony <toantranct94@gmail.com>
License-Expression: MIT
License-File: LICENSE
Classifier: Intended Audience :: Developers
Classifier: License :: OSI Approved :: MIT License
Classifier: Operating System :: OS Independent
Classifier: Programming Language :: Python
Classifier: Programming Language :: Python :: 3
Classifier: Programming Language :: Python :: 3 :: Only
Classifier: Programming Language :: Python :: 3.7
Classifier: Programming Language :: Python :: 3.8
Classifier: Programming Language :: Python :: 3.9
Classifier: Programming Language :: Python :: 3.10
Classifier: Programming Language :: Python :: 3.11
Classifier: Topic :: Software Development :: Build Tools
Classifier: Topic :: Software Development :: Libraries :: Python Modules
Requires-Dist: cookiecutter>=1.7.2
Requires-Dist: pydantic[email]>=1.7.2
Requires-Dist: questionary>=1.10.0
Requires-Dist: typer<0.7,>=0.4
